versioned_collection/__init__.py
versioned_collection/collection.py
versioned_collection/collection_store.py
versioned_collection/item.py
versioned_collection/persistence/__init__.py
versioned_collection/persistence/github.py
versioned_collection/persistence/json_file.py
versioned_collection/persistence/yaml_file.py
versioned_collection/serialization/__init__.py
versioned_collection/serialization/json.py
versioned_collection/serialization/yaml.py
versioned_collection/test_collection.py
versioned_collection/util/download_file.py
versioned_collection-0.0.1.dist-info/LICENSE
versioned_collection-0.0.1.dist-info/METADATA
versioned_collection-0.0.1.dist-info/WHEEL
versioned_collection-0.0.1.dist-info/RECORD
