Metadata-Version: 2.1
Name: versioned_collection
Version: 0.0.1
Summary: A Python library for storing and loading versioned collections of items searchable by key or value
License: Apache 2.0
Author: Roman Baron
Author-email: 1299323+RomansWorks@users.noreply.github.com
Requires-Python: >=3.9,<4.0
Classifier: License :: Other/Proprietary License
Classifier: Programming Language :: Python :: 3
Classifier: Programming Language :: Python :: 3.9
Classifier: Programming Language :: Python :: 3.10
Classifier: Programming Language :: Python :: 3.11
Classifier: Programming Language :: Python :: 3.12
Provides-Extra: http
Provides-Extra: yaml
Requires-Dist: aiohttp (>=3.9.1,<4.0.0) ; extra == "http"
Requires-Dist: pyyaml (>=6.0.1,<7.0.0) ; extra == "yaml"
